aptabase/__init__.py
aptabase/client.py
aptabase/exceptions.py
aptabase/models.py
aptabase-0.1.0.dist-info/METADATA
aptabase-0.1.0.dist-info/WHEEL
aptabase-0.1.0.dist-info/licenses/LICENSE
aptabase-0.1.0.dist-info/RECORD
