Metadata-Version: 2.4
Name: aptabase
Version: 0.1.0
Summary: Python SDK for Aptabase: Open Source, Privacy-First and Simple Analytics for Mobile, Desktop and Web Apps
Project-URL: Documentation, https://github.com/aptabase/aptabase-python
Project-URL: Issues, https://github.com/aptabase/aptabase-python/issues
Project-URL: Source, https://github.com/aptabase/aptabase-python
Author-email: Aptabase <support@aptabase.com>
License-Expression: MIT
License-File: LICENSE
Keywords: analytics,aptabase,async,privacy
Classifier: Intended Audience :: Developers
Classifier: Programming Language :: Python :: 3.11
Classifier: Programming Language :: Python :: 3.12
Classifier: Programming Language :: Python :: 3.13
Classifier: Topic :: Software Development :: Build Tools
Requires-Python: >=3.11
Requires-Dist: httpx>=0.28.1
